video2spectrogram/__init__.py
video2spectrogram/get_spectrogram.py
video2spectrogram-0.1.dist-info/LICENSE
video2spectrogram-0.1.dist-info/METADATA
video2spectrogram-0.1.dist-info/WHEEL
video2spectrogram-0.1.dist-info/top_level.txt
video2spectrogram-0.1.dist-info/RECORD
