Metadata-Version: 2.1
Name: video2spectrogram
Version: 0.1
Summary: Script for extracting audio and saving it in .WAV files and computing their Mel spectrogram and saving it in .JPEG file
Home-page: https://github.com/alexandrosstergiou/video2spectrogram
Author: Alexandros Stergiou
Author-email: alexstergiou5@gmail.com
License: MIT
Platform: UNKNOWN
License-File: LICENSE
